sr_tool/__init__.py
sr_tool/cli.py
sr_tool/main.py
sr_tool/sr_tool.py
sr_tool/test_RASU.py
sr_tool-0.1.0.dist-info/AUTHORS.rst
sr_tool-0.1.0.dist-info/LICENSE
sr_tool-0.1.0.dist-info/METADATA
sr_tool-0.1.0.dist-info/WHEEL
sr_tool-0.1.0.dist-info/entry_points.txt
sr_tool-0.1.0.dist-info/top_level.txt
sr_tool-0.1.0.dist-info/RECORD
