Metadata-Version: 2.1
Name: sr-tool
Version: 0.1.0
Summary: an integrated tool with SESR and SGSR to implement SR on LR images.
Home-page: https://github.com/yunot/sr_tool
Author: yunotao
Author-email: yunotao@163.com
License: MIT license
Keywords: sr_tool
Classifier: Development Status :: 2 - Pre-Alpha
Classifier: Intended Audience :: Developers
Classifier: License :: OSI Approved :: MIT License
Classifier: Natural Language :: English
Classifier: Programming Language :: Python :: 3
Classifier: Programming Language :: Python :: 3.6
Classifier: Programming Language :: Python :: 3.7
Classifier: Programming Language :: Python :: 3.8
Requires-Python: >=3.6
License-File: LICENSE
License-File: AUTHORS.rst
Requires-Dist: Click (>=7.0)
